{"images/burger.png":["images/burger.png"],"images/fried rice.jpg":["images/fried rice.jpg"],"images/ice-cream.png":["images/ice-cream.png"],"images/illustration1.jpg":["images/illustration1.jpg"],"images/illustration2.jpg":["images/illustration2.jpg"],"images/illustration3.jpg":["images/illustration3.jpg"],"images/jollof.jpg":["images/jollof.jpg"],"images/logo.png":["images/logo.png"],"images/pizza.png":["images/pizza.png"],"images/salad.png":["images/salad.png"],"packages/cupertino_icons/assets/CupertinoIcons.ttf":["packages/cupertino_icons/assets/CupertinoIcons.ttf"]}